sitesync/__init__.py
sitesync/sitesync.py
sitesync-1.0.3.data/scripts/sitesync
sitesync-1.0.3.dist-info/DESCRIPTION.rst
sitesync-1.0.3.dist-info/METADATA
sitesync-1.0.3.dist-info/RECORD
sitesync-1.0.3.dist-info/WHEEL
sitesync-1.0.3.dist-info/metadata.json
sitesync-1.0.3.dist-info/top_level.txt
