Metadata-Version: 2.0
Name: sitesync
Version: 1.0.3
Summary: Script to sync db and/or data from remote host
Home-page: https://github.com/morlandi/sitesync
Author: Mario Orlandi
Author-email: morlandi@brainstorm.it
License: MIT
Keywords: django database
Platform: UNKNOWN
Classifier: Development Status :: 3 - Alpha
Classifier: License :: OSI Approved :: MIT License
Classifier: Programming Language :: Python :: 2.7
Classifier: Programming Language :: Python :: 3.6
Classifier: Topic :: Database :: Database Engines/Servers
Classifier: Topic :: Internet
